ubergraph2asct/__init__.py
ubergraph2asct/__main__.py
ubergraph2asct/query.py
ubergraph2asct/ubergraph2asct.py
ubergraph2asct/utils/__ini__.py
ubergraph2asct/utils/query_utils.py
ubergraph2asct-0.1.0.dist-info/LICENSE
ubergraph2asct-0.1.0.dist-info/METADATA
ubergraph2asct-0.1.0.dist-info/WHEEL
ubergraph2asct-0.1.0.dist-info/entry_points.txt
ubergraph2asct-0.1.0.dist-info/RECORD
