Metadata-Version: 2.1
Name: ubergraph2asct
Version: 0.1.0
Summary: Generates ASCT table from Ubergraph
Home-page: https://github.com/hubmapconsortium/ubergraph2asct
License: http://www.apache.org/licenses/LICENSE-2.0
Author: Anita Caron
Author-email: anitacaron@users.noreply.github.com
Requires-Python: >=3.10,<4.0
Classifier: License :: Other/Proprietary License
Classifier: Programming Language :: Python :: 3
Classifier: Programming Language :: Python :: 3.10
Classifier: Programming Language :: Python :: 3.11
Requires-Dist: curies (>=0.7.4,<0.8.0)
Requires-Dist: networkx (>=3.2.1,<4.0.0)
Requires-Dist: oaklib (>=0.5.25,<0.6.0)
Requires-Dist: rdflib (>=7.0.0,<8.0.0)
Project-URL: Repository, https://github.com/hubmapconsortium/ubergraph2asct
